tcare_sbvalidator/__init__.py
tcare_sbvalidator/base_handler.py
tcare_sbvalidator/handlers.py
tcare_sbvalidator/models/__init__.py
tcare_sbvalidator/models/campaign_event.py
tcare_sbvalidator/models/email.py
tcare_sbvalidator/models/sms.py
tcare_sbvalidator/models/tcare_cloud_event.py
tcare_sbvalidator-0.0.49.dist-info/METADATA
tcare_sbvalidator-0.0.49.dist-info/WHEEL
tcare_sbvalidator-0.0.49.dist-info/licenses/LICENSE.txt
tcare_sbvalidator-0.0.49.dist-info/RECORD
