Metadata-Version: 2.1
Name: tcare_sbvalidator
Version: 0.0.49
Summary: Validate that servicebus messages are in the correct format
Project-URL: Homepage, https://github.com/TCARE1/tcare_sbvalidator
Project-URL: Bug Tracker, https://github.com/TCARE1/tcare_sbvalidator/issues
Author-email: TCARE <elijah.kennedy@tcare.ai>
License-File: LICENSE.txt
Classifier: License :: OSI Approved :: MIT License
Classifier: Operating System :: OS Independent
Classifier: Programming Language :: Python :: 3
Requires-Python: >=3.7
Requires-Dist: aiohttp
Requires-Dist: azure-identity
Requires-Dist: azure-servicebus
Requires-Dist: pydantic
Requires-Dist: websocket-client
